counter.v
module counter (
    input  wire clk,
    input  wire rst,
    output reg  [3:0] count
);

always @(posedge clk) begin
    if (rst)
        count <= 0;
    else
        count <= count + 1;
end
endmodule

tb_counter.v
module tb;

reg clk = 0;
reg rst = 1;
wire [3:0] count;

counter uut (
    .clk(clk),
    .rst(rst),
    .count(count)
);

// clock: 10 time units period
always #5 clk = ~clk;

initial begin
    $dumpfile("wave.vcd");
    $dumpvars(0, tb);

    #12 rst = 0;   // release reset
    #100 $finish;
end

endmodule

wave.vcd
$date
	Thu Dec 18 21:25:17 2025
$end
$version
	Icarus Verilog
$end
$timescale
	1s
$end
$scope module tb $end
$var wire 4 ! count [3:0] $end
$var reg 1 " clk $end
$var reg 1 # rst $end
$scope module uut $end
$var wire 1 " clk $end
$var wire 1 # rst $end
$var reg 4 $ count [3:0] $end
$upscope $end
$upscope $end
$enddefinitions $end
$comment Show the parameter values. $end
$dumpall
$end
#0
$dumpvars
bx $
1#
0"
bx !
$end
#5
b0 !
b0 $
1"
#10
0"
#12
0#
#15
b1 !
b1 $
1"
#20
0"
#25
b10 !
b10 $
1"
#30
0"
#35
b11 !
b11 $
1"
#40
0"
#45
b100 !
b100 $
1"
#50
0"
#55
b101 !
b101 $
1"
#60
0"
#65
b110 !
b110 $
1"
#70
0"
#75
b111 !
b111 $
1"
#80
0"
#85
b1000 !
b1000 $
1"
#90
0"
#95
b1001 !
b1001 $
1"
#100
0"
#105
b1010 !
b1010 $
1"
