Branch_Log/definitions.vh
// Testbenvh utilities:
`define assert(signal, value) \
if (signal !== value) $finish;

`define DATA_WIDTH 32


//Branch opcodes
`define BRANCH_BEQ 3'b000 // Branch Equal
`define BRANCH_BNE 3'b001 // Branch Not Equal
`define BRANCH_BLT 3'b100 // Branch Less Than
`define BRANCH_BGE 3'b101 // Branch Greater Than Or Equal
`define BRANCH_BLTU 3'b110 // Branch Less Than Unsigned
`define BRANCH_BGEU 3'b111 // Branch Greater Than Or Equal Unsigned
`define BRANCH_JAL_JALR 3'b010 // Jump in case of JAL or JALR instruction
// opcodes above are from funct3 field. Be careful with 010. It is not specified as a branch code in specs

Branch_Log/branch_log.v
// All definitions moved to definitions.vh
`include "definitions.vh"

module branch_log ( // In short, determines whether a branch should be taken based on certain conditions. The condition is specified via operation code, similar to ALU, and evaluated based on operands a and b.
    input wire i_branch, // Effectively an enable signal
    input wire [2:0] i_branch_op,
    input wire [`DATA_WIDTH-1:0] i_a,
    input wire [`DATA_WIDTH-1:0] i_b,
    output reg o_take //Take branch or no
);

wire signed [`DATA_WIDTH-1:0] i_a_sin = i_a; // I believe these both function as aliases, effectively. If not, will need to update inside the block
wire signed [`DATA_WIDTH-1:0] i_b_sin = i_b;

    always @* begin
        o_take = 0;
        if(i_branch) begin
            case (i_branch_op)
                `BRANCH_BEQ: begin
                    if(i_a == i_b) begin
                        o_take = 1;
                    end
                end

                `BRANCH_BNE: begin
                    if(i_a != i_b) begin
                        o_take = 1;
                    end
                end

                `BRANCH_BLT: begin
                    if(i_a_sin < i_b_sin) begin
                        o_take = 1;
                    end
                end

                `BRANCH_BGE: begin
                    if(i_a_sin >= i_b_sin) begin
                        o_take = 1;
                    end
                end

                `BRANCH_BLTU: begin
                    if(i_a < i_b) begin
                        o_take = 1;
                    end
                end

                `BRANCH_BGEU: begin
                    if(i_a >= i_b) begin
                        o_take = 1;
                    end
                end

              	`BRANCH_JAL_JALR: begin //Upon receiving appropriate instruction from deocde, will take branch, as is in-line with the instruction's use case.
              	//For JALR, later, remember the address jumped to is determined by ALU. Do not forget to wire that up.
                    o_take = 1;
                end
                default: o_take = 0;
            endcase
        end
    end

endmodule

Branch_Log/branch_log_tb.v
`include "definitions.vh"

// Unique to this tb rn. Will not move to definitions for now.
`define incrementpass \
        passed++;

module  branch_unit_tb;

  reg clk;
  reg i_branch = 1'b0;
  reg [2:0] i_branch_op = 3'b000;
  reg [`DATA_WIDTH-1:0] i_a = 32'h00000000;
  reg [`DATA_WIDTH-1:0] i_b = 32'h00000000;

  wire o_take;

  branch_log dut (
    .i_branch(i_branch),
    .i_branch_op(i_branch_op),
    .i_a(i_a),
    .i_b(i_b),
    .o_take(o_take)
  );

  reg [2:0] passed; //Counter intended to count the number of operations that work, in order tested in the testbench

  initial begin
    clk = 1'b0;
  end

  always #5 clk = ~clk;

  initial begin
    passed = 0;
    i_branch = 1'b1;
    i_a = 32'hA0000000;
    i_b = 32'hA0000000;
    i_branch_op = `BRANCH_BEQ;
    #10
      `assert(dut.o_take, 1'b1);
    i_b = 0;
    #10
      `assert(dut.o_take, 1'b0);// Tests equal op in case that arguments are equal and not equal
      `incrementpass //System Verilog. If testing with pure verilog interpreter, change. Others marked with //* and number of ops tested so you can find them easier
    i_branch = 0;
    #10;
      `assert(dut.o_take, 1'b0);// Tests that enable signal (i_branch) works properly. Not an operation
    i_branch = 1;
    i_b = 32'hA0000000;
    i_branch_op = `BRANCH_BNE;
    #10
      `assert(dut.o_take, 1'b0);
    i_b = 0;
    #10
      `assert(dut.o_take, 1'b1);
    i_b = 32'hA0000000;
    i_a = 0;
    #10
      `assert(dut.o_take, 1'b1);
      `incrementpass//* 2
    i_branch_op = `BRANCH_BLT;
    #10
      `assert(dut.o_take, 1'b0);
    i_b = 0;
    #10
      `assert(dut.o_take, 1'b0);
    i_a = 32'hB000000B;
    #10
      `assert(dut.o_take, 1'b1);
      `incrementpass//* 3
    i_branch_op = `BRANCH_BGE;
    #10
      `assert(dut.o_take, 1'b0);
    i_b = i_a;
    #10
      `assert(dut.o_take, 1'b1);
    i_a = 0;
    #10
      `assert(dut.o_take, 1'b1);
      `incrementpass//* 4
    i_branch_op = `BRANCH_BLTU;
    i_a = 0;
    #10
      `assert(dut.o_take, 1'b1);
    i_b = 0;
    #10
      `assert(dut.o_take, 1'b0);
    i_a = 32'hB000000B;
    #10
      `assert(dut.o_take, 1'b0);
      `incrementpass//* 5
    i_branch_op = `BRANCH_BGEU;
    #10
      `assert(dut.o_take, 1'b1);
    i_b = i_a;
    #10
      `assert(dut.o_take, 1'b1);
    i_a = 0;
    #10
      `assert(dut.o_take, 1'b0);
      `incrementpass//* 6
    i_branch_op = `BRANCH_JAL_JALR;
    #10
      `assert(dut.o_take, 1'b1)
      `incrementpass//* 7
    #10;
    i_branch_op = 3'b011;// Testing the one illegal opcode; not an operation; should default to 0
    #10
      `assert(dut.o_take, 1'b0)
      `incrementpass //* 8
      //Even though it isn't an operation, I feel the need to signal it is complete some way
    #10
    $finish;

  end

  initial begin
    $dumpfile("Branch_Log/wave.vcd");
    $dumpvars;
  end

endmodule

Branch_Log/wave.vcd
$date
	Sun May 17 15:30:36 2026
$end
$version
	Icarus Verilog
$end
$timescale
	1s
$end
$scope module branch_unit_tb $end
$var wire 1 ! o_take $end
$var reg 1 " clk $end
$var reg 32 # i_a [31:0] $end
$var reg 32 $ i_b [31:0] $end
$var reg 1 % i_branch $end
$var reg 3 & i_branch_op [2:0] $end
$var reg 3 ' passed [2:0] $end
$scope module dut $end
$var wire 32 ( i_a [31:0] $end
$var wire 32 ) i_a_sin [31:0] $end
$var wire 32 * i_b [31:0] $end
$var wire 32 + i_b_sin [31:0] $end
$var wire 1 % i_branch $end
$var wire 3 , i_branch_op [2:0] $end
$var reg 1 ! o_take $end
$upscope $end
$upscope $end
$enddefinitions $end
$comment Show the parameter values. $end
$dumpall
$end
#0
$dumpvars
b0 ,
b10100000000000000000000000000000 +
b10100000000000000000000000000000 *
b10100000000000000000000000000000 )
b10100000000000000000000000000000 (
b0 '
b0 &
1%
b10100000000000000000000000000000 $
b10100000000000000000000000000000 #
0"
1!
$end
#5
1"
#10
0!
0"
b0 +
b0 $
b0 *
#15
1"
#20
0"
0%
b1 '
#25
1"
#30
0"
b1 &
b1 ,
b10100000000000000000000000000000 +
b10100000000000000000000000000000 $
b10100000000000000000000000000000 *
1%
#35
1"
#40
1!
0"
b0 +
b0 $
b0 *
#45
1"
#50
1!
0"
b0 )
b0 #
b0 (
b10100000000000000000000000000000 +
b10100000000000000000000000000000 $
b10100000000000000000000000000000 *
#55
1"
#60
0!
0"
b100 &
b100 ,
b10 '
#65
1"
#70
0"
b0 +
b0 $
b0 *
#75
1"
#80
1!
0"
b10110000000000000000000000001011 )
b10110000000000000000000000001011 #
b10110000000000000000000000001011 (
#85
1"
#90
0!
0"
b101 &
b101 ,
b11 '
#95
1"
#100
1!
0"
b10110000000000000000000000001011 +
b10110000000000000000000000001011 $
b10110000000000000000000000001011 *
#105
1"
#110
1!
0"
b0 )
b0 #
b0 (
#115
1"
#120
1!
0"
b110 &
b110 ,
b100 '
#125
1"
#130
0!
0"
b0 +
b0 $
b0 *
#135
1"
#140
0"
b10110000000000000000000000001011 )
b10110000000000000000000000001011 #
b10110000000000000000000000001011 (
#145
1"
#150
1!
0"
b111 &
b111 ,
b101 '
#155
1"
#160
1!
0"
b10110000000000000000000000001011 +
b10110000000000000000000000001011 $
b10110000000000000000000000001011 *
#165
1"
#170
0!
0"
b0 )
b0 #
b0 (
#175
1"
#180
1!
0"
b10 &
b10 ,
b110 '
#185
1"
#190
0"
b111 '
#195
1"
#200
0!
0"
b11 &
b11 ,
#205
1"
#210
0"
b0 '
