tb_sanitation/tb_standard.vh

// clock: 10 time units period
always #5 clk = ~clk;

initial begin
    // new release reset, less arbitrary than #12
    rst = 1'b1;
    repeat (2) @(posedge clk);
    rst = 1'b0;

    repeat (20) @(posedge clk);

    $finish;
end

counter.v
module counter (
    input  wire clk,
    input  wire rst,
    output reg  [3:0] count
);

always @(posedge clk) begin
    if (rst)
        count <= 0;
    else
        count <= count + 1;
end
endmodule

Counter/tb_counter.v
module tb;

reg clk = 0;
reg rst = 1;
wire [3:0] count;

// Remember to invoke simulator from ../RV32-Base, not a lower directory or includes may not work properly
`include "../tb_sanitation/tb_standard.vh"

counter uut (
    .clk(clk),
    .rst(rst),
    .count(count)
);

initial begin
    $dumpfile("Counter/wave.vcd");
    $dumpvars(0, tb);
end

endmodule

Counter/wave.vcd
$date
	Fri Dec 19 23:13:30 2025
$end
$version
	Icarus Verilog
$end
$timescale
	1s
$end
$scope module tb $end
$var wire 4 ! count [3:0] $end
$var reg 1 " clk $end
$var reg 1 # rst $end
$scope module uut $end
$var wire 1 " clk $end
$var wire 1 # rst $end
$var reg 4 $ count [3:0] $end
$upscope $end
$upscope $end
$enddefinitions $end
$comment Show the parameter values. $end
$dumpall
$end
#0
$dumpvars
bx $
1#
0"
bx !
$end
#5
b0 !
b0 $
1"
#10
0"
#15
0#
1"
#20
0"
#25
b1 !
b1 $
1"
#30
0"
#35
b10 !
b10 $
1"
#40
0"
#45
b11 !
b11 $
1"
#50
0"
#55
b100 !
b100 $
1"
#60
0"
#65
b101 !
b101 $
1"
#70
0"
#75
b110 !
b110 $
1"
#80
0"
#85
b111 !
b111 $
1"
#90
0"
#95
b1000 !
b1000 $
1"
#100
0"
#105
b1001 !
b1001 $
1"
#110
0"
#115
b1010 !
b1010 $
1"
#120
0"
#125
b1011 !
b1011 $
1"
#130
0"
#135
b1100 !
b1100 $
1"
#140
0"
#145
b1101 !
b1101 $
1"
#150
0"
#155
b1110 !
b1110 $
1"
#160
0"
#165
b1111 !
b1111 $
1"
#170
0"
#175
b0 !
b0 $
1"
#180
0"
#185
b1 !
b1 $
1"
#190
0"
#195
b10 !
b10 $
1"
#200
0"
#205
b11 !
b11 $
1"
#210
0"
#215
b100 !
b100 $
1"
