ALU/ALU.v
// Note on operation codes (numbers right of definition)
// First four bits define class (arithmetic, logic, and, for lack of better terminology, setting operations (abs, SLT, SLL, etc))
// Latter four bits specify sub operation within each class (add, sub, and, etc)

// RISC-V ALU Operations
`define OP_ALU_NOP    8'b00000000 // Zero/"Universal Identity" operation
`define OP_ALU_ADD    8'b00010001 // Add
`define OP_ALU_SUB    8'b00010010 // Subtract
`define OP_ALU_AND    8'b00100001 // Bitwise AND
`define OP_ALU_OR     8'b00100010 // Bitwise OR
`define OP_ALU_XOR    8'b00100011 // Bitwise XOR
`define OP_ALU_SLT    8'b00110101 // Set Less Than (signed)
//`define OP_ALU_SLTU   8'b00110010 // Set Less Than (unsigned)  //Currently disabled. Sticking with just SLT for now
`define OP_ALU_SLL    8'b00110011 // Shift Left Logical
`define OP_ALU_SRL    8'b00110100 // Shift Right Logical
`define OP_ALU_SRA    8'b00110101 // Shift Right Arithmetic

// Additional operations outside basics (though still pretty basic). Includes RV32M operations (MUL,DIV)
// Will likely be expanded later
`define OP_ALU_INV    8'b00100100 // Bitwise Inversion (NOT operation)
`define OP_ALU_MUL    8'b00010011 // Multiplication
`define OP_ALU_DIV    8'b00010100 // Division
`define OP_ALU_MOD    8'b00010101 // Modulus

`define DATA_WIDTH 32

module alu (
    input wire [5:0] i_alu_op,
    input wire [31:0] i_a,
    input wire [31:0] i_b,
    output reg [31:0] o_c
);

    always @* begin
        case (i_alu_op)
            `OP_ALU_ADD:    o_c = i_a + i_b;
            `OP_ALU_SUB:    o_c = i_a - i_b;
            `OP_ALU_AND:    o_c = i_a&i_b;
            `OP_ALU_OR:     o_c = i_a|i_b;
            `OP_ALU_XOR:    o_c = (i_a|i_b)&(~(i_a&i_b));
            `OP_ALU_SLT:
            begin
                if(i_a<i_b) o_c = 1;
                else o_c = 0;
            end
            /*`OP_ALU_SLTU:
            begin
                if($signed(i_a) < $signed(i_b)) o_c = 1;
                else o_c = 0;
            end*/
            `OP_ALU_SLL:    o_c = i_a << i_b[4:0];
            `OP_ALU_SRL:    o_c = i_a >> i_b[4:0];
            `OP_ALU_SRA:    o_c = $signed(i_a) >>> i_b[4:0];
            `OP_ALU_INV:    o_c = ~i_a;
            `OP_ALU_MUL:    ;
            `OP_ALU_DIV:    ;
            `OP_ALU_MOD:    ;
            default: o_c = 0;
        endcase
    end

endmodule

//(i_a < i_b) ? 32'h1 : 32'h0

ALU/ALU_tb.v
`define assert(signal, value) \
        if (signal !== value) $finish;

module  alu_tb;

  reg clk;
  reg [5:0] i_alu_op = 5'b00000;
  reg [`DATA_WIDTH-1:0] i_a = 32'h00000000;
  reg [`DATA_WIDTH-1:0] i_b = 32'h00000000;

  wire [`DATA_WIDTH-1:0] o_c;

  alu dut (
    .i_alu_op(i_alu_op),
    .i_a(i_a),
    .i_b(i_b),
    .o_c(o_c)
  );

  initial begin
    clk = 1'b0;
  end

  always #5 clk = ~clk;

  initial begin
        i_a = 32'h00000001;
        i_b = 32'h00000001;
        i_alu_op = `OP_ALU_ADD;
      #5
        `assert(dut.o_c, 32'h00000002);
        i_a = 32'h00000001;
        i_b = 32'h00000001;
        i_alu_op = `OP_ALU_SUB;
      #5;
        `assert(dut.o_c, 32'h00000000);
        i_a = 32'h00001001;
        i_b = 32'h00100001;
        i_alu_op = `OP_ALU_AND;
      #5;
        `assert(dut.o_c, 32'h00000001);
        i_a = 32'h00000101;
        i_b = 32'h00010001;
        i_alu_op = `OP_ALU_OR;
      #5;
        `assert(dut.o_c, 32'h00010101);
        i_a = 32'h00000101;
        i_b = 32'h00010001;
        i_alu_op = `OP_ALU_XOR;
      #5;
        `assert(dut.o_c, 32'h00010100);
        i_a = 32'h00000001;
        i_b = 32'h00000001;
        i_alu_op = `OP_ALU_INV;
      #5;
        `assert(dut.o_c,32'hfffffffe);
        i_a = 32'h00000101;
        i_b = 32'h00010001;
        i_alu_op = `OP_ALU_SLT;
      #5;
        `assert(dut.o_c, 32'h00000001);
        i_a = 32'h00000001;
        i_b = 32'h00000010;
        i_alu_op = `OP_ALU_SLL;
      #5;
        `assert(dut.o_c, 32'h00010000);
        i_a = 32'h00000100;
        i_b = 32'h00000001;
        i_alu_op = `OP_ALU_SRL;
      #5;
        `assert(dut.o_c, 32'h00000080);
        i_a = 32'hfffffff0;
        i_b = 32'h00000003;
        i_alu_op = `OP_ALU_SRA;
      #5;
        `assert(dut.o_c, 32'hfffffffe);
         i_a = 32'h80000000;
         i_b = 32'h0000001f;
         i_alu_op = `OP_ALU_SRA;
       #5;
        `assert(dut.o_c, 32'hffffffff);

    $finish;

  end

  initial begin
    $dumpfile("ALU/wave.vcd");
    $dumpvars;
  end

endmodule

ALU/wave.vcd
$date
	Sat Jan  3 11:38:53 2026
$end
$version
	Icarus Verilog
$end
$timescale
	1s
$end
$scope module alu_tb $end
$var wire 32 ! o_c [31:0] $end
$var reg 1 " clk $end
$var reg 32 # i_a [31:0] $end
$var reg 6 $ i_alu_op [5:0] $end
$var reg 32 % i_b [31:0] $end
$scope module dut $end
$var wire 32 & i_a [31:0] $end
$var wire 6 ' i_alu_op [5:0] $end
$var wire 32 ( i_b [31:0] $end
$var reg 32 ) o_c [31:0] $end
$upscope $end
$upscope $end
$enddefinitions $end
$comment Show the parameter values. $end
$dumpall
$end
#0
$dumpvars
b10 )
b1 (
b10001 '
b1 &
b1 %
b10001 $
b1 #
0"
b10 !
$end
#5
b0 !
b0 )
b10010 $
b10010 '
1"
#10
b1 !
b1 )
b100001 $
b100001 '
b100000000000000000001 %
b100000000000000000001 (
b1000000000001 #
b1000000000001 &
0"
#15
b10000000100000001 !
b10000000100000001 )
b100010 $
b100010 '
b10000000000000001 %
b10000000000000001 (
b100000001 #
b100000001 &
1"
#20
b10000000100000000 !
b10000000100000000 )
b100011 $
b100011 '
0"
#25
b11111111111111111111111111111110 !
b11111111111111111111111111111110 )
b100100 $
b100100 '
b1 %
b1 (
b1 #
b1 &
1"
#30
b1 !
b1 )
b110101 $
b110101 '
b10000000000000001 %
b10000000000000001 (
b100000001 #
b100000001 &
0"
#35
b10000000000000000 !
b10000000000000000 )
b110011 $
b110011 '
b10000 %
b10000 (
b1 #
b1 &
1"
#40
b10000000 !
b10000000 )
b110100 $
b110100 '
b1 %
b1 (
b100000000 #
b100000000 &
0"
#45
b0 !
b0 )
b110101 $
b110101 '
b11 %
b11 (
b11111111111111111111111111110000 #
b11111111111111111111111111110000 &
1"
