definitions.vh
// Testbench utilities:
`define assert(signal, value) \
if (signal !== value) $finish;

`define DATA_WIDTH 32
`define INST_WIDTH 32
`define NUM_REGISTER 32
`define FUNCT7_WIDTH 7


// Instruction opcodes (identify type of instruction being fetched)
//From included image of RV32I base instruction set
`define Rtype   7'b0110011
`define Itype_A 7'b0010011 //Arithmetic
`define Itype_L 7'b0000011 //Load
`define Stype   7'b0100011
`define Btype   7'b1100011
`define Utype   7'b0110111
`define Jtype   7'b1101111


//Branch opcodes
`define BRANCH_BEQ 3'b000 // Branch Equal
`define BRANCH_BNE 3'b001 // Branch Not Equal
`define BRANCH_BLT 3'b100 // Branch Less Than
`define BRANCH_BGE 3'b101 // Branch Greater Than Or Equal
`define BRANCH_BLTU 3'b110 // Branch Less Than Unsigned
`define BRANCH_BGEU 3'b111 // Branch Greater Than Or Equal Unsigned
`define BRANCH_JAL_JALR 3'b010 // Jump in case of JAL or JALR instruction
// opcodes above are from funct3 field. Be careful with 010. It is not specified as a branch code in specs


// Note on operation codes for ALU
// First four bits define class (arithmetic, logic, and, for lack of better terminology, setting operations (abs, SLT, SLL, etc))
// Latter four bits specify sub operation within each class (add, sub, and, etc)

//ALU ops
`define OP_ALU_NOP    7'b00000000 // Zero/"Universal Identity" operation
`define OP_ALU_ADD    7'b0010001 // Add
`define OP_ALU_SUB    7'b0010010 // Subtract
`define OP_ALU_AND    7'b0100001 // Bitwise AND
`define OP_ALU_OR     7'b0100010 // Bitwise OR
`define OP_ALU_XOR    7'b0100011 // Bitwise XOR
`define OP_ALU_SLT    7'b0110001 // Set Less Than (signed)
`define OP_ALU_SLTU   7'b0110010 // Set Less Than (unsigned)
`define OP_ALU_SLL    7'b0110011 // Shift Left Logical
`define OP_ALU_SRL    7'b0110100 // Shift Right Logical
`define OP_ALU_SRA    7'b0110101 // Shift Right Arithmetic

// Additional operations outside basics (though still pretty basic). Includes RV32M operations (MUL,DIV) and custom operations
// Will likely be expanded later
`define OP_ALU_INV    7'b0100100 // Bitwise Inversion (NOT operation)
`define OP_ALU_MUL    7'b0010011 // Multiplication
`define OP_ALU_DIV    7'b0010100 // Division
`define OP_ALU_MOD    7'b0010101 // Modulus

ALU/ALU.v
`include "definitions.vh"

module alu (
    input wire [7:0] i_alu_op,
    input wire [`DATA_WIDTH-1:0] i_a,
    input wire [`DATA_WIDTH-1:0] i_b,
    output reg [`DATA_WIDTH-1:0] o_c
);

    always @* begin
        case (i_alu_op)
            `OP_ALU_ADD:    o_c = i_a + i_b;
            `OP_ALU_SUB:    o_c = i_a - i_b;
            `OP_ALU_AND:    o_c = i_a&i_b;
            `OP_ALU_OR:     o_c = i_a|i_b;
            `OP_ALU_XOR:    o_c = (i_a|i_b)&(~(i_a&i_b));
            `OP_ALU_SLT:
            begin
                if(i_a<i_b) o_c = 1;
                else o_c = 0;
            end
            `OP_ALU_SLTU:
            begin
                if(i_a < i_b) o_c = 1;
                else o_c = 0;
            end
            `OP_ALU_SLL:    o_c = i_a << i_b[4:0];
            `OP_ALU_SRL:    o_c = i_a >> i_b[4:0];
            `OP_ALU_SRA:    o_c = $signed(i_a) >>> i_b[4:0];
            `OP_ALU_INV:    o_c = ~i_a;
            `OP_ALU_MUL:
            begin
                logic [63:0] prod;
                prod = $signed(i_a) * $signed(i_b);
                o_c  = prod[`DATA_WIDTH-1:0];
            end
            `OP_ALU_DIV:
            begin
                if (i_b == 32'h0) o_c = 32'hffffffff;
                else if (i_a == 32'h80000000 && i_b == 32'hffffffff) o_c = 32'h80000000;
                else o_c = $signed(i_a) / $signed(i_b);
            end
            `OP_ALU_MOD:
            begin
                if (i_b == 32'h0) o_c = i_a;
                else if (i_a == 32'h8000_0000 && i_b == 32'hffff_ffff) o_c = 32'h0;
                else o_c = $signed(i_a) % $signed(i_b);
            end
            `OP_ALU_NOP:// Explicit case for NOP rather than just relying on default
            begin
                o_c = 32'h0;
            end

            default: o_c = 0;
        endcase
    end

endmodule

//(i_a < i_b) ? 32'h1 : 32'h0

ALU/ALU_tb.v
module  alu_tb;

  reg clk;
  reg [7:0] i_alu_op = 8'b00000000;
  reg [`DATA_WIDTH-1:0] i_a = 32'h00000000;
  reg [`DATA_WIDTH-1:0] i_b = 32'h00000000;

  wire [`DATA_WIDTH-1:0] o_c;

  alu dut (
    .i_alu_op(i_alu_op),
    .i_a(i_a),
    .i_b(i_b),
    .o_c(o_c)
  );

  initial begin
    clk = 1'b0;
  end

  always #5 clk = ~clk;

  initial begin
        i_a = 32'h00000001;
        i_b = 32'h00000001;
        i_alu_op = `OP_ALU_ADD;
      #5
        `assert(dut.o_c, 32'h00000002);
        i_a = 32'h00000001;
        i_b = 32'h00000001;
        i_alu_op = `OP_ALU_SUB;
      #5;
        `assert(dut.o_c, 32'h00000000);
        i_a = 32'h00001001;
        i_b = 32'h00100001;
        i_alu_op = `OP_ALU_AND;
      #5;
        `assert(dut.o_c, 32'h00000001);
        i_a = 32'h00000101;
        i_b = 32'h00010001;
        i_alu_op = `OP_ALU_OR;
      #5;
        `assert(dut.o_c, 32'h00010101);
        i_a = 32'h00000101;
        i_b = 32'h00010001;
        i_alu_op = `OP_ALU_XOR;
      #5;
        `assert(dut.o_c, 32'h00010100);
        i_a = 32'h00000001;
        i_alu_op = `OP_ALU_INV;
      #5;
        `assert(dut.o_c,32'hfffffffe);
        i_a = 32'h00000101;
        i_b = 32'h00010001;
        i_alu_op = `OP_ALU_SLT;
      #5;
        `assert(dut.o_c, 32'h00000001);
        i_a = 32'h00000001;
        i_b = 32'hA0A0B0B0;
        i_alu_op = `OP_ALU_SLTU;
      #5;
        `assert(dut.o_c,32'h00000001);
        i_a = 32'h00000001;
        i_b = 32'h00000010;
        i_alu_op = `OP_ALU_SLL;
      #5;
        `assert(dut.o_c, 32'h00010000);
        i_a = 32'h00000100;
        i_b = 32'h00000001;
        i_alu_op = `OP_ALU_SRL;
      #5;
        `assert(dut.o_c, 32'h00000080);
        i_a = 32'hfffffff0;
        i_b = 32'h00000003;
        i_alu_op = `OP_ALU_SRA;
      #5;
        `assert(dut.o_c, 32'hfffffffe);
         i_a = 32'h80000000;
         i_b = 32'h0000001f;
         i_alu_op = `OP_ALU_SRA;
       #5;
        `assert(dut.o_c, 32'hffffffff);
        i_a = 32'h00000002;
        i_b = 32'h00000002;
        i_alu_op = `OP_ALU_MUL;
       #5;
        `assert(dut.o_c, 32'h00000004);
        i_a = 32'h00000005;
        i_b = 32'h00000005;
        i_alu_op = `OP_ALU_DIV;
       #5;
        `assert(dut.o_c, 32'h00000001);
        i_a = 32'h00000007;
        i_b = 32'h00000005;
        i_alu_op = `OP_ALU_MOD;
       #5;
        `assert(dut.o_c, 32'h00000002);
        i_a = 32'hAABBAABB;
        i_b = 32'h99009900;
        i_alu_op = `OP_ALU_NOP;
       #5;
        `assert(dut.o_c,32'h0);
       #3; //Odd time to make it easier to tell if it finished
    $finish;

  end

  initial begin
    $dumpfile("ALU/wave.vcd");
    $dumpvars;
  end

endmodule

ALU/wave.vcd
$date
	Sat May 23 14:35:15 2026
$end
$version
	Icarus Verilog
$end
$timescale
	1s
$end
$scope module alu_tb $end
$var wire 32 ! o_c [31:0] $end
$var reg 1 " clk $end
$var reg 32 # i_a [31:0] $end
$var reg 8 $ i_alu_op [7:0] $end
$var reg 32 % i_b [31:0] $end
$scope module dut $end
$var wire 32 & i_a [31:0] $end
$var wire 8 ' i_alu_op [7:0] $end
$var wire 32 ( i_b [31:0] $end
$var reg 32 ) o_c [31:0] $end
$scope begin $unm_blk_4 $end
$var reg 64 * prod [63:0] $end
$upscope $end
$upscope $end
$upscope $end
$enddefinitions $end
$comment Show the parameter values. $end
$dumpall
$end
#0
$dumpvars
bx *
b10 )
b1 (
b10001 '
b1 &
b1 %
b10001 $
b1 #
0"
b10 !
$end
#5
b0 !
b0 )
b10010 $
b10010 '
1"
#10
b1 !
b1 )
b100001 $
b100001 '
b100000000000000000001 %
b100000000000000000001 (
b1000000000001 #
b1000000000001 &
0"
#15
b10000000100000001 !
b10000000100000001 )
b100010 $
b100010 '
b10000000000000001 %
b10000000000000001 (
b100000001 #
b100000001 &
1"
#20
b10000000100000000 !
b10000000100000000 )
b100011 $
b100011 '
0"
#25
b11111111111111111111111111111110 !
b11111111111111111111111111111110 )
b100100 $
b100100 '
b1 #
b1 &
1"
#30
b1 !
b1 )
b110001 $
b110001 '
b100000001 #
b100000001 &
0"
#35
b110010 $
b110010 '
b10100000101000001011000010110000 %
b10100000101000001011000010110000 (
b1 #
b1 &
1"
#40
b10000000000000000 !
b10000000000000000 )
b110011 $
b110011 '
b10000 %
b10000 (
0"
#45
b10000000 !
b10000000 )
b110100 $
b110100 '
b1 %
b1 (
b100000000 #
b100000000 &
1"
#50
b11111111111111111111111111111110 !
b11111111111111111111111111111110 )
b110101 $
b110101 '
b11 %
b11 (
b11111111111111111111111111110000 #
b11111111111111111111111111110000 &
0"
#55
b11111111111111111111111111111111 !
b11111111111111111111111111111111 )
b11111 %
b11111 (
b10000000000000000000000000000000 #
b10000000000000000000000000000000 &
1"
#60
b100 !
b100 )
b100 *
b10011 $
b10011 '
b10 %
b10 (
b10 #
b10 &
0"
#65
b1 !
b1 )
b10100 $
b10100 '
b101 %
b101 (
b101 #
b101 &
1"
#70
b10 !
b10 )
b10101 $
b10101 '
b111 #
b111 &
0"
#75
b0 !
b0 )
b0 $
b0 '
b10011001000000001001100100000000 %
b10011001000000001001100100000000 (
b10101010101110111010101010111011 #
b10101010101110111010101010111011 &
1"
